vulnscanner/__init__.py
vulnscanner/crawler.py
vulnscanner/export_report.py
vulnscanner/form_scanner.py
vulnscanner/gui.py
vulnscanner/main.py
vulnscanner/report_generator.py
vulnscanner/sqli_scanner.py
vulnscanner/subdomain_scanner.py
vulnscanner/utils.py
vulnscanner/xss_scanner.py
sqli_vuln_scanner-1.0.0.dist-info/METADATA
sqli_vuln_scanner-1.0.0.dist-info/WHEEL
sqli_vuln_scanner-1.0.0.dist-info/entry_points.txt
sqli_vuln_scanner-1.0.0.dist-info/top_level.txt
sqli_vuln_scanner-1.0.0.dist-info/RECORD
