Metadata-Version: 2.4
Name: sqli-vuln-scanner
Version: 1.0.0
Summary: An advanced SQLi, XSS, and Form vulnerability scanner
Author: Rupesh Jha
Classifier: Programming Language :: Python :: 3
Classifier: License :: OSI Approved :: MIT License
Requires-Python: >=3.6
Requires-Dist: requests
Requires-Dist: beautifulsoup4
Requires-Dist: colorama
Requires-Dist: fpdf
Dynamic: author
Dynamic: classifier
Dynamic: requires-dist
Dynamic: requires-python
Dynamic: summary
